betty/__init__.py
betty/engine.py
betty/test_install.py
betty/utils.py
betty/version.txt
betty/configs/__init__.py
betty/configs/engine_dataclass.py
betty/configs/problem_dataclass.py
betty/envs/__init__.py
betty/envs/env_base.py
betty/hypergradient/__init__.py
betty/hypergradient/cg.py
betty/hypergradient/darts.py
betty/hypergradient/neumann.py
betty/hypergradient/reinforce.py
betty/hypergradient/sama.py
betty/hypergradient/utils.py
betty/logging/__init__.py
betty/logging/logger_base.py
betty/logging/logger_tensorboard.py
betty/logging/logger_wandb.py
betty/misc/__init__.py
betty/misc/early_stopping.py
betty/optim/__init__.py
betty/optim/adam.py
betty/optim/adamw.py
betty/optim/optimizer.py
betty/optim/sgd.py
betty/patch/__init__.py
betty/patch/data_loader.py
betty/patch/optimizer.py
betty/patch/scheduler.py
betty/problems/__init__.py
betty/problems/implicit_problem.py
betty/problems/iterative_problem.py
betty/problems/iterative_problem_higher.py
betty/problems/problem.py
betty/rl/__init__.py
betty/rl/buffer.py
betty_ml-0.2.1.dist-info/LICENSE
betty_ml-0.2.1.dist-info/WHEEL
betty_ml-0.2.1.dist-info/METADATA
betty_ml-0.2.1.dist-info/RECORD
