Metadata-Version: 2.1
Name: betty-ml
Version: 0.2.1
Summary: Betty: an automatic differentiation library for generalized meta-learning and multilevel optimization
Author-email: Sang Keun Choe <sangkeun00@gmail.com>
Requires-Python: >=3.6,<3.11
Classifier: License :: OSI Approved :: Apache Software License
Requires-Dist: torch>=1.8.0
Requires-Dist: numpy>=1.9.0
Project-URL: Home, https://github.com/leopard-ai/betty
